conftab/__init__.py
conftab/ctl.py
conftab/default.py
conftab/function.py
conftab/model.py
conftab/modelmid.py
conftab/modelsecret.py
conftab/security.py
conftab/tab.py
conftab/version.py
conftab/web.py
conftab/cyhper/__init__.py
conftab/cyhper/des.py
conftab/cyhper/rsa.py
conftab/cyhper/rsa_demo.py
conftab/utils/__init__.py
conftab-1.1.2.dist-info/LICENSE
conftab-1.1.2.dist-info/METADATA
conftab-1.1.2.dist-info/WHEEL
conftab-1.1.2.dist-info/top_level.txt
conftab-1.1.2.dist-info/RECORD
