Metadata-Version: 2.1
Name: conftab
Version: 1.1.2
Summary: config version manager with web or code easily
Home-page: https://github.com/DJMIN/conftab
Author: readerror
Author-email: readerror@sina.com
Maintainer: readerror
Maintainer-email: readerror@sina.com
License: GPL License
Platform: all
Requires-Python: >=3.7
License-File: LICENSE
Requires-Dist: fastapi
Requires-Dist: requests
Requires-Dist: uvicorn
Requires-Dist: click
Requires-Dist: sqlalchemy
Requires-Dist: python-multipart
Requires-Dist: wheel
Requires-Dist: twine
Requires-Dist: pycryptodome
Requires-Dist: werkzeug
Requires-Dist: pydantic
Requires-Dist: python-jose
Requires-Dist: guesstime
